pywidgets_ext/__init__.py
pywidgets_ext/PyFigureCanvas.py
pywidgets_ext/PyGraphicsView.py
pywidgets_ext-0.1.5.dist-info/LICENSE
pywidgets_ext-0.1.5.dist-info/METADATA
pywidgets_ext-0.1.5.dist-info/WHEEL
pywidgets_ext-0.1.5.dist-info/RECORD
