Metadata-Version: 2.1
Name: pywidgets-ext
Version: 0.1.5
Summary: 
Home-page: https://pypi.org/project/pywidgets-ext/
License: MIT
Author: Leo
Author-email: jafee201153@gmail.com
Requires-Python: >=3.9,<3.12
Classifier: License :: OSI Approved :: MIT License
Classifier: Programming Language :: Python :: 3
Classifier: Programming Language :: Python :: 3.9
Classifier: Programming Language :: Python :: 3.10
Classifier: Programming Language :: Python :: 3.11
Requires-Dist: matplotlib (>=3.8.0,<4.0.0)
Requires-Dist: pyside6 (>=6.5.2,<7.0.0)
Project-URL: Repository, https://github.com/leoli0605/pywidgets-ext
